.gitignore
.travis.yml
LICENSE
MANIFEST.in
Makefile
README.md
setup.cfg
setup.py
test_requirements.txt
mozilla_taar2.egg-info/PKG-INFO
mozilla_taar2.egg-info/SOURCES.txt
mozilla_taar2.egg-info/dependency_links.txt
mozilla_taar2.egg-info/not-zip-safe
mozilla_taar2.egg-info/requires.txt
mozilla_taar2.egg-info/top_level.txt
taar/__init__.py
taar/profile_fetcher.py
taar/adapters/__init__.py
taar/adapters/dynamo.py
taar/adapters/tests/__init__.py
taar/recommenders/__init__.py
taar/recommenders/base_recommender.py
taar/recommenders/collaborative_recommender.py
taar/recommenders/ensemble_recommender.py
taar/recommenders/legacy_recommender.py
taar/recommenders/locale_recommender.py
taar/recommenders/recommendation_manager.py
taar/recommenders/similarity_recommender.py
taar/recommenders/utils.py
taar/tests/__init__.py
tests/__init__.py
tests/mocks.py
tests/similarity_data.py
tests/test_collaborativerecommender.py
tests/test_ensemblerecommender.py
tests/test_legacyrecommender.py
tests/test_localerecommender.py
tests/test_profile_fetcher.py
tests/test_recommendation_manager.py
tests/test_similarityrecommender.py
tests/test_utils.py